example_pdf/__init__.py
example_pdf/admin.py
example_pdf/apps.py
example_pdf/models.py
example_pdf/tests.py
example_pdf/views.py
example_pdf/migrations/0001_initial.py
example_pdf/migrations/__init__.py
pass_PdfExport/__init__.py
pass_PdfExport/asgi.py
pass_PdfExport/settings.py
pass_PdfExport/urls.py
pass_PdfExport/wsgi.py
pdfExport/__init__.py
pdfExport/admin.py
pdfExport/apps.py
pdfExport/models.py
pdfExport/tests.py
pdfExport/views.py
pdfExport/templates/pdfExport/base_pdf_template.html
pdfExport/templates/pdfExport/pdf_export_change_form.html
qz_pdf_export-0.1.6.dist-info/METADATA
qz_pdf_export-0.1.6.dist-info/WHEEL
qz_pdf_export-0.1.6.dist-info/top_level.txt
qz_pdf_export-0.1.6.dist-info/RECORD
