Metadata-Version: 2.1
Name: qz_pdf_export
Version: 0.1.6
Summary: 方便快捷的pdf导出工具
Home-page: 
Author: qz
Author-email: 2902934039@qq.com
Classifier: Framework :: Django
Classifier: Programming Language :: Python :: 3
Requires-Python: >=3.10
